nix_nox-0.0.6.dist-info/DESCRIPTION.rst
nix_nox-0.0.6.dist-info/METADATA
nix_nox-0.0.6.dist-info/RECORD
nix_nox-0.0.6.dist-info/WHEEL
nix_nox-0.0.6.dist-info/entry_points.txt
nix_nox-0.0.6.dist-info/metadata.json
nix_nox-0.0.6.dist-info/pbr.json
nix_nox-0.0.6.dist-info/top_level.txt
nox/cache.py
nox/nixpkgs_repo.py
nox/review.py
nox/search.py
nox/update.py
nox/tests/__init__.py
nox/tests/test_review.py
