Metadata-Version: 2.0
Name: nix-nox
Version: 0.0.6
Summary: Tools to make nix nicer to use
Home-page: UNKNOWN
Author: Georges Dubus
Author-email: georges.dubus@compiletoi.net
License: BSD
Platform: UNKNOWN
Requires-Dist: characteristic
Requires-Dist: click
Requires-Dist: dogpile.cache
Requires-Dist: requests
